pearai_mcp/__init__.py
pearai_mcp/constants.py
pearai_mcp/server.py
pearai_mcp/deploy/__init__.py
pearai_mcp/deploy/deploy.py
pearai_mcp/templates/__init__.py
pearai_mcp/templates/template_service.py
pearai_mcp-0.1.8.dist-info/METADATA
pearai_mcp-0.1.8.dist-info/WHEEL
pearai_mcp-0.1.8.dist-info/entry_points.txt
pearai_mcp-0.1.8.dist-info/RECORD
