Metadata-Version: 2.4
Name: pearai-mcp
Version: 0.1.8
Summary: PearAI MCP
Author-email: PearAI <ops@trypear.ai>
Requires-Python: >=3.12
Requires-Dist: aiohttp>=3.9.0
Requires-Dist: mcp>=1.4.0
Requires-Dist: requests>=2.31.0
